{
  "ok": true,
  "status": "static",
  "placeId": "86378115369061",
  "rootPlaceId": "86378115369061",
  "universeId": "10230921598",
  "name": "+1 Backflip Obby Escape",
  "creatorName": "Jump = Backflip",
  "creatorType": "Group",
  "playing": 33755,
  "visits": 27386007,
  "favorites": 2246880,
  "likes": 19486,
  "dislikes": 1977,
  "thumbnailUrl": "https://tr.rbxcdn.com/180DAY-d49555b0a7b4658cac5482bbe9a06525/512/512/Image/Png/noFilter",
  "robloxUrl": "https://www.roblox.com/games/86378115369061",
  "fetchedAtUtc": "2026-06-21 20:35:27"
}
