{
  "ok": true,
  "status": "static",
  "placeId": "9224601490",
  "rootPlaceId": "9224601490",
  "universeId": "3457700596",
  "name": "[OPE V2] Fruit Battlegrounds",
  "creatorName": "P O P O",
  "creatorType": "Group",
  "playing": 3860,
  "visits": 1045303550,
  "favorites": 989829,
  "likes": 1119082,
  "dislikes": 128035,
  "thumbnailUrl": "https://tr.rbxcdn.com/180DAY-5b331270d0a5c1096a3acc6cf62b0414/512/512/Image/Png/noFilter",
  "robloxUrl": "https://www.roblox.com/games/9224601490",
  "fetchedAtUtc": "2026-06-26 11:00:46",
  "chartData": {
    "schemaVersion": 1,
    "updatedAt": "2026-06-26 11:00:46",
    "updatedAtTs": 1782471646,
    "source": "roblox",
    "sourceIntervalSeconds": null,
    "retention": {
      "playerHistorySeconds": 604800
    },
    "summary": {
      "current": [
        1782471646,
        3860
      ],
      "peak7d": [
        1782471646,
        3860
      ]
    },
    "series": {
      "players": [
        [
          1782467730,
          3782
        ],
        [
          1782468043,
          3745
        ],
        [
          1782468329,
          3783
        ],
        [
          1782468633,
          3756
        ],
        [
          1782468935,
          3763
        ],
        [
          1782469233,
          3738
        ],
        [
          1782469530,
          3796
        ],
        [
          1782469841,
          3826
        ],
        [
          1782470126,
          3792
        ],
        [
          1782470433,
          3763
        ],
        [
          1782470731,
          3835
        ],
        [
          1782471034,
          3803
        ],
        [
          1782471331,
          3788
        ],
        [
          1782471646,
          3860
        ]
      ]
    }
  }
}
