{
  "ok": true,
  "status": "static",
  "placeId": "10449761463",
  "rootPlaceId": "10449761463",
  "universeId": "3808081382",
  "name": "The Strongest Battlegrounds",
  "creatorName": "Yielding Arts",
  "creatorType": "Group",
  "playing": 62564,
  "visits": 18449187069,
  "favorites": 7305508,
  "likes": 5147804,
  "dislikes": 981530,
  "thumbnailUrl": "https://tr.rbxcdn.com/180DAY-68c92fc62a8753793f7963e146b5197f/512/512/Image/Png/noFilter",
  "robloxUrl": "https://www.roblox.com/games/10449761463",
  "fetchedAtUtc": "2026-06-22 22:50:38"
}
