{
  "ok": true,
  "status": "static",
  "placeId": "606849621",
  "rootPlaceId": "606849621",
  "universeId": "245662005",
  "name": "🎊 [CH 4] Jailbreak",
  "creatorName": "Badimo",
  "creatorType": "Group",
  "playing": 14608,
  "visits": 7933874300,
  "favorites": 18589639,
  "likes": 5767252,
  "dislikes": 807671,
  "thumbnailUrl": "https://tr.rbxcdn.com/180DAY-37ea1de2efc4f4844d2d39d2b2c57f64/512/512/Image/Png/noFilter",
  "robloxUrl": "https://www.roblox.com/games/606849621",
  "fetchedAtUtc": "2026-06-23 00:25:27",
  "chartData": {
    "schemaVersion": 1,
    "updatedAt": "2026-06-23 00:25:27",
    "updatedAtTs": 1782174327,
    "source": "roblox",
    "sourceIntervalSeconds": null,
    "retention": {
      "playerHistorySeconds": 604800
    },
    "summary": {
      "current": [
        1782174327,
        14608
      ],
      "peak7d": [
        1782174327,
        14608
      ]
    },
    "series": {
      "players": [
        [
          1782174030,
          14597
        ],
        [
          1782174327,
          14608
        ]
      ]
    }
  }
}
