{
  "ok": true,
  "status": "static",
  "placeId": "97598239454123",
  "rootPlaceId": "97598239454123",
  "universeId": "10200395747",
  "name": "Grow a Garden 2",
  "creatorName": "Strawberreh Squad",
  "creatorType": "Group",
  "playing": 433196,
  "visits": 484022713,
  "favorites": 427288,
  "likes": 494542,
  "dislikes": 52943,
  "thumbnailUrl": "https://tr.rbxcdn.com/180DAY-319c616b7699d893e22e6641221d0782/512/512/Image/Png/noFilter",
  "robloxUrl": "https://www.roblox.com/games/97598239454123",
  "fetchedAtUtc": "2026-06-22 04:55:27"
}
