{
  "ok": true,
  "status": "static",
  "placeId": "71132543521245",
  "rootPlaceId": "71132543521245",
  "universeId": "8356066619",
  "name": "[🌘UPD 0.5🩸] Anime Squadron",
  "creatorName": "Komplex Studio",
  "creatorType": "Group",
  "playing": 56289,
  "visits": 20060537,
  "favorites": 24902,
  "likes": 42604,
  "dislikes": 1870,
  "thumbnailUrl": "https://tr.rbxcdn.com/180DAY-f2f99a1ac248135961833d6223ecfd4b/512/512/Image/Png/noFilter",
  "robloxUrl": "https://www.roblox.com/games/71132543521245",
  "fetchedAtUtc": "2026-06-21 01:15:31"
}
