{
  "ok": true,
  "status": "static",
  "placeId": "9391468976",
  "rootPlaceId": "9391468976",
  "universeId": "3508322461",
  "name": "[BLACK DEATH] Jujutsu Shenanigans",
  "creatorName": "Tze's Shenanigans",
  "creatorType": "Group",
  "playing": 139817,
  "visits": 5981641898,
  "favorites": 2628673,
  "likes": 2328680,
  "dislikes": 351642,
  "thumbnailUrl": "https://tr.rbxcdn.com/180DAY-e27277bbda2ba2efdb47a1863df2da3d/512/512/Image/Png/noFilter",
  "robloxUrl": "https://www.roblox.com/games/9391468976",
  "fetchedAtUtc": "2026-06-22 14:00:50"
}
