{
  "ok": true,
  "status": "static",
  "placeId": "98664161516921",
  "rootPlaceId": "98664161516921",
  "universeId": "9141743926",
  "name": "[🏰] Catch a Monster",
  "creatorName": "LDS II",
  "creatorType": "Group",
  "playing": 16277,
  "visits": 356256482,
  "favorites": 550449,
  "likes": 500752,
  "dislikes": 10636,
  "thumbnailUrl": "https://tr.rbxcdn.com/180DAY-0e256b37d77ad642efaf017c8013daf1/512/512/Image/Png/noFilter",
  "robloxUrl": "https://www.roblox.com/games/98664161516921",
  "fetchedAtUtc": "2026-06-24 04:40:33",
  "chartData": {
    "schemaVersion": 1,
    "updatedAt": "2026-06-24 04:40:33",
    "updatedAtTs": 1782276033,
    "source": "roblox",
    "sourceIntervalSeconds": null,
    "retention": {
      "playerHistorySeconds": 604800
    },
    "summary": {
      "current": [
        1782276033,
        16277
      ],
      "peak7d": [
        1782221442,
        18182
      ]
    },
    "series": {
      "players": [
        [
          1782174030,
          17723
        ],
        [
          1782174327,
          17725
        ],
        [
          1782174643,
          17747
        ],
        [
          1782174926,
          17694
        ],
        [
          1782175231,
          17611
        ],
        [
          1782175532,
          17656
        ],
        [
          1782175832,
          17617
        ],
        [
          1782176128,
          17545
        ],
        [
          1782176450,
          17621
        ],
        [
          1782176729,
          17589
        ],
        [
          1782177031,
          17537
        ],
        [
          1782177331,
          17592
        ],
        [
          1782177632,
          17690
        ],
        [
          1782177930,
          17751
        ],
        [
          1782178240,
          17770
        ],
        [
          1782178526,
          17777
        ],
        [
          1782178832,
          17733
        ],
        [
          1782179131,
          17854
        ],
        [
          1782179436,
          17897
        ],
        [
          1782179726,
          17756
        ],
        [
          1782180044,
          17757
        ],
        [
          1782180329,
          17698
        ],
        [
          1782180634,
          17639
        ],
        [
          1782180935,
          17696
        ],
        [
          1782181231,
          17732
        ],
        [
          1782181527,
          17752
        ],
        [
          1782181840,
          17782
        ],
        [
          1782182132,
          17781
        ],
        [
          1782182436,
          17779
        ],
        [
          1782182731,
          17909
        ],
        [
          1782183034,
          17773
        ],
        [
          1782183328,
          17624
        ],
        [
          1782183644,
          17620
        ],
        [
          1782183929,
          17631
        ],
        [
          1782184232,
          17450
        ],
        [
          1782184532,
          17453
        ],
        [
          1782184836,
          17445
        ],
        [
          1782185124,
          17374
        ],
        [
          1782185440,
          17480
        ],
        [
          1782185732,
          17522
        ],
        [
          1782186037,
          17462
        ],
        [
          1782186331,
          17429
        ],
        [
          1782186632,
          17481
        ],
        [
          1782186927,
          17460
        ],
        [
          1782187242,
          17541
        ],
        [
          1782187530,
          17558
        ],
        [
          1782187831,
          17454
        ],
        [
          1782188133,
          17443
        ],
        [
          1782188433,
          17501
        ],
        [
          1782188727,
          17384
        ],
        [
          1782189040,
          17413
        ],
        [
          1782189327,
          17435
        ],
        [
          1782189631,
          17374
        ],
        [
          1782189934,
          17373
        ],
        [
          1782190232,
          17368
        ],
        [
          1782190525,
          17234
        ],
        [
          1782190846,
          17222
        ],
        [
          1782191126,
          17159
        ],
        [
          1782191446,
          17051
        ],
        [
          1782191733,
          17121
        ],
        [
          1782192033,
          17195
        ],
        [
          1782192326,
          17121
        ],
        [
          1782192641,
          17214
        ],
        [
          1782192926,
          17235
        ],
        [
          1782193231,
          17151
        ],
        [
          1782193531,
          16656
        ],
        [
          1782193832,
          16760
        ],
        [
          1782194127,
          16773
        ],
        [
          1782194446,
          16775
        ],
        [
          1782194728,
          16830
        ],
        [
          1782195038,
          16777
        ],
        [
          1782195331,
          16759
        ],
        [
          1782195634,
          16777
        ],
        [
          1782195928,
          16735
        ],
        [
          1782196238,
          16761
        ],
        [
          1782196528,
          16908
        ],
        [
          1782196832,
          16826
        ],
        [
          1782197145,
          16942
        ],
        [
          1782197431,
          16864
        ],
        [
          1782197729,
          16837
        ],
        [
          1782198049,
          16994
        ],
        [
          1782198329,
          17002
        ],
        [
          1782198632,
          16873
        ],
        [
          1782198935,
          16981
        ],
        [
          1782199236,
          16960
        ],
        [
          1782199534,
          16986
        ],
        [
          1782199846,
          17091
        ],
        [
          1782200131,
          17050
        ],
        [
          1782200440,
          16946
        ],
        [
          1782200734,
          17023
        ],
        [
          1782201038,
          17072
        ],
        [
          1782201329,
          17105
        ],
        [
          1782201649,
          17102
        ],
        [
          1782201934,
          17125
        ],
        [
          1782202234,
          17038
        ],
        [
          1782202532,
          17145
        ],
        [
          1782202841,
          17133
        ],
        [
          1782203131,
          17022
        ],
        [
          1782203444,
          17051
        ],
        [
          1782203737,
          17156
        ],
        [
          1782204039,
          17151
        ],
        [
          1782204379,
          17132
        ],
        [
          1782204638,
          17076
        ],
        [
          1782204926,
          17059
        ],
        [
          1782205248,
          17062
        ],
        [
          1782205529,
          17055
        ],
        [
          1782205840,
          16920
        ],
        [
          1782206132,
          16843
        ],
        [
          1782206436,
          17003
        ],
        [
          1782206731,
          17041
        ],
        [
          1782207045,
          16952
        ],
        [
          1782207328,
          16965
        ],
        [
          1782207637,
          16952
        ],
        [
          1782207937,
          16904
        ],
        [
          1782208234,
          17060
        ],
        [
          1782208525,
          16878
        ],
        [
          1782208844,
          16902
        ],
        [
          1782209132,
          16929
        ],
        [
          1782209437,
          16813
        ],
        [
          1782209736,
          16882
        ],
        [
          1782210040,
          16928
        ],
        [
          1782210347,
          16947
        ],
        [
          1782210638,
          17025
        ],
        [
          1782210929,
          17050
        ],
        [
          1782211231,
          17025
        ],
        [
          1782211535,
          17041
        ],
        [
          1782211835,
          17102
        ],
        [
          1782212129,
          17077
        ],
        [
          1782212446,
          17096
        ],
        [
          1782212733,
          17033
        ],
        [
          1782213033,
          16953
        ],
        [
          1782213333,
          17052
        ],
        [
          1782213633,
          17231
        ],
        [
          1782213931,
          17271
        ],
        [
          1782214242,
          17309
        ],
        [
          1782214526,
          17447
        ],
        [
          1782214837,
          17447
        ],
        [
          1782215132,
          17380
        ],
        [
          1782215435,
          17399
        ],
        [
          1782215728,
          17400
        ],
        [
          1782216053,
          17566
        ],
        [
          1782216325,
          17567
        ],
        [
          1782216638,
          17543
        ],
        [
          1782216933,
          17594
        ],
        [
          1782217240,
          17693
        ],
        [
          1782217530,
          17636
        ],
        [
          1782217848,
          17781
        ],
        [
          1782218128,
          17819
        ],
        [
          1782218434,
          17752
        ],
        [
          1782218732,
          17884
        ],
        [
          1782219038,
          17848
        ],
        [
          1782219328,
          17830
        ],
        [
          1782219651,
          18018
        ],
        [
          1782219932,
          17998
        ],
        [
          1782220236,
          17914
        ],
        [
          1782220532,
          17935
        ],
        [
          1782220835,
          18046
        ],
        [
          1782221130,
          18065
        ],
        [
          1782221442,
          18182
        ],
        [
          1782221730,
          18146
        ],
        [
          1782222043,
          18059
        ],
        [
          1782222339,
          18081
        ],
        [
          1782222639,
          18047
        ],
        [
          1782222931,
          17952
        ],
        [
          1782223250,
          17931
        ],
        [
          1782223536,
          17969
        ],
        [
          1782223842,
          18027
        ],
        [
          1782224137,
          18156
        ],
        [
          1782224437,
          18114
        ],
        [
          1782224732,
          18007
        ],
        [
          1782225041,
          18110
        ],
        [
          1782225333,
          18008
        ],
        [
          1782225637,
          17992
        ],
        [
          1782225937,
          17968
        ],
        [
          1782226236,
          18158
        ],
        [
          1782226532,
          18065
        ],
        [
          1782227133,
          18008
        ],
        [
          1782227438,
          17931
        ],
        [
          1782227738,
          18038
        ],
        [
          1782228041,
          18067
        ],
        [
          1782228336,
          17874
        ],
        [
          1782228652,
          17804
        ],
        [
          1782228933,
          17816
        ],
        [
          1782229243,
          17769
        ],
        [
          1782229537,
          17769
        ],
        [
          1782229835,
          17741
        ],
        [
          1782230133,
          17613
        ],
        [
          1782230456,
          17696
        ],
        [
          1782230734,
          17671
        ],
        [
          1782231038,
          17709
        ],
        [
          1782231356,
          17790
        ],
        [
          1782231640,
          17909
        ],
        [
          1782231941,
          17777
        ],
        [
          1782232270,
          17859
        ],
        [
          1782233133,
          17852
        ],
        [
          1782233434,
          17921
        ],
        [
          1782233729,
          17762
        ],
        [
          1782234055,
          17660
        ],
        [
          1782234334,
          17580
        ],
        [
          1782234640,
          17436
        ],
        [
          1782234938,
          17459
        ],
        [
          1782235231,
          17429
        ],
        [
          1782235532,
          17294
        ],
        [
          1782235849,
          17333
        ],
        [
          1782236133,
          17264
        ],
        [
          1782236439,
          17266
        ],
        [
          1782236737,
          17276
        ],
        [
          1782237038,
          17263
        ],
        [
          1782237333,
          17217
        ],
        [
          1782237652,
          17234
        ],
        [
          1782237935,
          17269
        ],
        [
          1782238259,
          17248
        ],
        [
          1782238534,
          17271
        ],
        [
          1782238838,
          17236
        ],
        [
          1782239150,
          17207
        ],
        [
          1782239446,
          17087
        ],
        [
          1782239729,
          17091
        ],
        [
          1782240039,
          17004
        ],
        [
          1782240339,
          17022
        ],
        [
          1782240634,
          17005
        ],
        [
          1782240937,
          16906
        ],
        [
          1782241265,
          16896
        ],
        [
          1782241536,
          16949
        ],
        [
          1782241834,
          16839
        ],
        [
          1782242142,
          16749
        ],
        [
          1782242438,
          16730
        ],
        [
          1782242733,
          16591
        ],
        [
          1782243045,
          16539
        ],
        [
          1782243331,
          16487
        ],
        [
          1782243650,
          16456
        ],
        [
          1782243939,
          16452
        ],
        [
          1782244238,
          16474
        ],
        [
          1782244541,
          16378
        ],
        [
          1782244872,
          16330
        ],
        [
          1782245132,
          16286
        ],
        [
          1782245452,
          16292
        ],
        [
          1782245736,
          16294
        ],
        [
          1782246036,
          16231
        ],
        [
          1782246332,
          16168
        ],
        [
          1782246642,
          16203
        ],
        [
          1782246925,
          16236
        ],
        [
          1782247233,
          16151
        ],
        [
          1782247529,
          16113
        ],
        [
          1782247831,
          16166
        ],
        [
          1782248126,
          16148
        ],
        [
          1782248450,
          16062
        ],
        [
          1782248725,
          16016
        ],
        [
          1782249035,
          15945
        ],
        [
          1782249363,
          15955
        ],
        [
          1782249640,
          15927
        ],
        [
          1782249927,
          15838
        ],
        [
          1782250241,
          15870
        ],
        [
          1782250525,
          15864
        ],
        [
          1782250832,
          15722
        ],
        [
          1782251131,
          15752
        ],
        [
          1782251434,
          15667
        ],
        [
          1782251727,
          15571
        ],
        [
          1782252045,
          15560
        ],
        [
          1782252326,
          15486
        ],
        [
          1782252633,
          15487
        ],
        [
          1782252933,
          15451
        ],
        [
          1782253231,
          15442
        ],
        [
          1782253528,
          15346
        ],
        [
          1782253840,
          15336
        ],
        [
          1782254127,
          15290
        ],
        [
          1782254436,
          15231
        ],
        [
          1782254732,
          15329
        ],
        [
          1782255034,
          15289
        ],
        [
          1782255330,
          15308
        ],
        [
          1782255645,
          15294
        ],
        [
          1782255928,
          15341
        ],
        [
          1782256236,
          15282
        ],
        [
          1782256531,
          15241
        ],
        [
          1782256834,
          15330
        ],
        [
          1782257127,
          15269
        ],
        [
          1782257439,
          15342
        ],
        [
          1782257728,
          15398
        ],
        [
          1782258032,
          15399
        ],
        [
          1782258330,
          15364
        ],
        [
          1782258631,
          15392
        ],
        [
          1782258926,
          15344
        ],
        [
          1782259247,
          15482
        ],
        [
          1782259527,
          16038
        ],
        [
          1782259834,
          16174
        ],
        [
          1782260134,
          16153
        ],
        [
          1782260431,
          16062
        ],
        [
          1782260727,
          15998
        ],
        [
          1782261042,
          16073
        ],
        [
          1782261326,
          16170
        ],
        [
          1782261638,
          16115
        ],
        [
          1782261935,
          16158
        ],
        [
          1782262233,
          16222
        ],
        [
          1782262529,
          16188
        ],
        [
          1782262847,
          16231
        ],
        [
          1782263127,
          16263
        ],
        [
          1782263474,
          16288
        ],
        [
          1782263731,
          16283
        ],
        [
          1782264031,
          16335
        ],
        [
          1782264333,
          16168
        ],
        [
          1782264642,
          16226
        ],
        [
          1782264931,
          16196
        ],
        [
          1782265233,
          16221
        ],
        [
          1782265530,
          16293
        ],
        [
          1782265836,
          16316
        ],
        [
          1782266125,
          16304
        ],
        [
          1782266447,
          16323
        ],
        [
          1782266729,
          16381
        ],
        [
          1782267036,
          16362
        ],
        [
          1782267334,
          16358
        ],
        [
          1782267636,
          16451
        ],
        [
          1782267930,
          16416
        ],
        [
          1782268245,
          16371
        ],
        [
          1782268532,
          16355
        ],
        [
          1782268830,
          16288
        ],
        [
          1782269133,
          16400
        ],
        [
          1782269433,
          16478
        ],
        [
          1782269729,
          16427
        ],
        [
          1782270047,
          16371
        ],
        [
          1782270328,
          16375
        ],
        [
          1782270633,
          16284
        ],
        [
          1782270933,
          16267
        ],
        [
          1782271234,
          16307
        ],
        [
          1782271531,
          16227
        ],
        [
          1782271841,
          16267
        ],
        [
          1782272125,
          16370
        ],
        [
          1782272437,
          16306
        ],
        [
          1782272728,
          16382
        ],
        [
          1782273032,
          16345
        ],
        [
          1782273326,
          16357
        ],
        [
          1782273646,
          16387
        ],
        [
          1782273926,
          16343
        ],
        [
          1782274235,
          16230
        ],
        [
          1782274532,
          16255
        ],
        [
          1782274837,
          16312
        ],
        [
          1782275128,
          16242
        ],
        [
          1782275443,
          16281
        ],
        [
          1782275726,
          16300
        ],
        [
          1782276033,
          16277
        ]
      ]
    }
  }
}
